ftw/__init__.py
ftw/simple.py
simple_ftw-0.0.8.dist-info/LICENSE
simple_ftw-0.0.8.dist-info/METADATA
simple_ftw-0.0.8.dist-info/WHEEL
simple_ftw-0.0.8.dist-info/top_level.txt
simple_ftw-0.0.8.dist-info/RECORD
