Metadata-Version: 2.1
Name: simple-ftw
Version: 0.0.8
Summary: my first published package
Home-page: https://github.com/fiona-tw/ftw
Author: Fiona Tahta-Wraith
Author-email: fionatw@outlook.com
License: UNKNOWN
Platform: UNKNOWN
Classifier: Programming Language :: Python :: 3
Classifier: License :: OSI Approved :: MIT License
Classifier: Operating System :: OS Independent
Requires-Python: >=3.7
